README.md
setup.py
ecoji/__init__.py
ecoji/__main__.py
ecoji/mapping.py
ecoji.egg-info/PKG-INFO
ecoji.egg-info/SOURCES.txt
ecoji.egg-info/dependency_links.txt
ecoji.egg-info/entry_points.txt
ecoji.egg-info/top_level.txt
tests/__init__.py
tests/__main__.py
tests/test_decode.py
tests/test_encode.py