Metadata-Version: 1.1
Name: ecoji
Version: 0.1.0
Summary: Encode and decode data as emojis.
Home-page: https://github.com/mecforlove/ecoji-py
Author: mecforlove
Author-email: mecforlove@outlook.com
License: Apache
Platform: UNKNOWN
Classifier: Programming Language :: Python
Classifier: Programming Language :: Python :: 3
